[
  {
    "inputs": [
      {
        "internalType": "address",
        "name": "_tokenIn",
        "type": "address"
      },
      {
        "internalType": "uint256",
        "name": "_amountIn",
        "type": "uint256"
      },
      {
        "internalType": "address",
        "name": "_sender",
        "type": "address"
      }
    ],
    "name": "getAmountOut",
    "outputs": [
      {
        "internalType": "uint256",
        "name": "_amountOut",
        "type": "uint256"
      }
    ],
    "stateMutability": "view",
    "type": "function"
  },
  {
    "inputs": [],
    "name": "getReserves",
    "outputs": [
      {
        "internalType": "uint256",
        "name": "_reserve0",
        "type": "uint256"
      },
      {
        "internalType": "uint256",
        "name": "_reserve1",
        "type": "uint256"
      }
    ],
    "stateMutability": "view",
    "type": "function"
  },
  {
    "inputs": [],
    "name": "token0",
    "outputs": [
      {
        "internalType": "address",
        "name": "",
        "type": "address"
      }
    ],
    "stateMutability": "view",
    "type": "function"
  },
  {
    "inputs": [],
    "name": "token1",
    "outputs": [
      {
        "internalType": "address",
        "name": "",
        "type": "address"
      }
    ],
    "stateMutability": "view",
    "type": "function"
  },
  {
    "inputs": [],
    "name": "invariantLast",
    "outputs": [
      {
        "internalType": "uint256",
        "name": "",
        "type": "uint256"
      }
    ],
    "stateMutability": "view",
    "type": "function"
  },
  {
    "anonymous": false,
    "inputs": [
      {
        "indexed": true,
        "internalType": "address",
        "name": "from",
        "type": "address"
      },
      {
        "indexed": true,
        "internalType": "address",
        "name": "to",
        "type": "address"
      },
      {
        "indexed": false,
        "internalType": "uint256",
        "name": "value",
        "type": "uint256"
      }
    ],
    "name": "Transfer",
    "type": "event"
  },
  {
    "inputs": [],
    "name": "totalSupply",
    "outputs": [
      {
        "internalType": "uint256",
        "name": "",
        "type": "uint256"
      }
    ],
    "stateMutability": "view",
    "type": "function"
  },
  {
    "inputs": [
      {
        "internalType": "address",
        "name": "account",
        "type": "address"
      }
    ],
    "name": "balanceOf",
    "outputs": [
      {
        "internalType": "uint256",
        "name": "",
        "type": "uint256"
      }
    ],
    "stateMutability": "view",
    "type": "function"
  },
  {
    "inputs": [],
    "name": "master",
    "outputs": [
      {
        "internalType": "address",
        "name": "",
        "type": "address"
      }
    ],
    "stateMutability": "view",
    "type": "function"
  },
  {
    "anonymous": false,
    "inputs": [
      {
        "indexed": true,
        "internalType": "address",
        "name": "sender",
        "type": "address"
      },
      {
        "indexed": false,
        "internalType": "uint256",
        "name": "amount0",
        "type": "uint256"
      },
      {
        "indexed": false,
        "internalType": "uint256",
        "name": "amount1",
        "type": "uint256"
      },
      {
        "indexed": false,
        "internalType": "uint256",
        "name": "liquidity",
        "type": "uint256"
      },
      {
        "indexed": true,
        "internalType": "address",
        "name": "to",
        "type": "address"
      }
    ],
    "name": "Mint",
    "type": "event"
  },
  {
    "anonymous": false,
    "inputs": [
      {
        "indexed": true,
        "internalType": "address",
        "name": "sender",
        "type": "address"
      },
      {
        "indexed": false,
        "internalType": "uint256",
        "name": "amount0",
        "type": "uint256"
      },
      {
        "indexed": false,
        "internalType": "uint256",
        "name": "amount1",
        "type": "uint256"
      },
      {
        "indexed": false,
        "internalType": "uint256",
        "name": "liquidity",
        "type": "uint256"
      },
      {
        "indexed": true,
        "internalType": "address",
        "name": "to",
        "type": "address"
      }
    ],
    "name": "Burn",
    "type": "event"
  },
  {
    "anonymous": false,
    "inputs": [
      {
        "indexed": false,
        "internalType": "uint256",
        "name": "reserve0",
        "type": "uint256"
      },
      {
        "indexed": false,
        "internalType": "uint256",
        "name": "reserve1",
        "type": "uint256"
      }
    ],
    "name": "Sync",
    "type": "event"
  }
]
